pathmonkey/__init__.py
pathmonkey/pathmonkey.py
pathmonkey-0.0.1.dist-info/LICENSE
pathmonkey-0.0.1.dist-info/METADATA
pathmonkey-0.0.1.dist-info/WHEEL
pathmonkey-0.0.1.dist-info/top_level.txt
pathmonkey-0.0.1.dist-info/RECORD
