Metadata-Version: 2.2
Name: pathmonkey
Version: 0.0.1
Summary: A utility to help with python paths on linux and windows
Author-email: Good Boy <pythonic@rexbytes.com>
License: MIT License
Project-URL: Repository, https://github.com/RexBytes/pathmonkey
Project-URL: Bug Tracker, https://github.com/RexBytes/pathmonkey
Classifier: Development Status :: 4 - Beta
Classifier: Intended Audience :: Developers
Classifier: Programming Language :: Python :: 3.9
Classifier: Programming Language :: Python :: 3.10
Classifier: Programming Language :: Python :: 3.11
Classifier: Programming Language :: Python :: 3.12
Classifier: License :: OSI Approved :: MIT License
Classifier: Operating System :: OS Independent
Classifier: Topic :: Software Development :: Libraries :: Python Modules
Requires-Python: <3.13,>=3.9
License-File: LICENSE
Provides-Extra: dev
Requires-Dist: pytest; extra == "dev"
